NeuralNetworkCoordinates/NeuralNetworkCoordinates.py
NeuralNetworkCoordinates/__init__.py
NeuralNetworkCoordinates-1.0.0.dist-info/LICENSE.txt
NeuralNetworkCoordinates-1.0.0.dist-info/METADATA
NeuralNetworkCoordinates-1.0.0.dist-info/WHEEL
NeuralNetworkCoordinates-1.0.0.dist-info/top_level.txt
NeuralNetworkCoordinates-1.0.0.dist-info/RECORD
